engine.py
esf.py
esf-1.0.3.dist-info/DESCRIPTION.rst
esf-1.0.3.dist-info/METADATA
esf-1.0.3.dist-info/RECORD
esf-1.0.3.dist-info/WHEEL
esf-1.0.3.dist-info/metadata.json
esf-1.0.3.dist-info/top_level.txt
